<included>
    <appender name="STDOUT" class="ch.qos.logback.core.ConsoleAppender">
        <encoder class="net.logstash.logback.encoder.LogstashEncoder">
            <fieldNames>
                <timestamp>timestamp</timestamp>
                <thread>thread</thread>
                <logger>logger</logger>
                <version>version</version>
                <mdc>mdc</mdc>
                <message>message</message>
            </fieldNames>
        </encoder>
    </appender>

    <appender name="ASYNC500" class="ch.qos.logback.classic.AsyncAppender">
        <queueSize>500</queueSize>
        <discardingThreshold>0</discardingThreshold>
        <appender-ref ref="STDOUT" />
    </appender>

    <root level="DEBUG">
        <appender-ref ref="ASYNC500"/>
    </root>
</included>
